chamberenv
