Metadata-Version: 2.1
Name: chamberenv
Version: 0.0.4
Summary: Manage chamber environments.
Home-page: https://github.com/normoes/chamberenv
Author: Norman Moeschter-Schenck
Author-email: norman.moeschter@gmail.com
License: UNKNOWN
Download-URL: https://github.com/normoes/chamberenv/archive/v0.0.4.tar.gz
Platform: UNKNOWN
Classifier: Development Status :: 5 - Production/Stable
Classifier: Intended Audience :: Developers
Classifier: License :: OSI Approved :: MIT License
Classifier: Natural Language :: English
Classifier: Programming Language :: Python
